glyph/__init__.py
glyph/_version.py
glyph/application.py
glyph/assessment.py
glyph/observer.py
glyph/cli/__init__.py
glyph/cli/_parser.py
glyph/cli/glyph_remote.py
glyph/gp/__init__.py
glyph/gp/algorithms.py
glyph/gp/breeding.py
glyph/gp/constraints.py
glyph/gp/individual.py
glyph/utils/__init__.py
glyph/utils/argparse.py
glyph/utils/break_condition.py
glyph/utils/logging.py
glyph/utils/numeric.py
pyglyph-0.5.3.dist-info/LICENCE
pyglyph-0.5.3.dist-info/METADATA
pyglyph-0.5.3.dist-info/WHEEL
pyglyph-0.5.3.dist-info/entry_points.txt
pyglyph-0.5.3.dist-info/top_level.txt
pyglyph-0.5.3.dist-info/RECORD
