Metadata-Version: 2.1
Name: pyglyph
Version: 0.5.3
Summary: Symbolic regression tools.
Home-page: https://github.com/Ambrosys/glyph
Author: Markus Abel, Julien Gout, Markus Quade
Author-email: markus.quade@ambrosys.de
License: LGPL
Keywords: complex systems,control,machine learning,genetic programming
Platform: UNKNOWN
Classifier: Development Status :: 3 - Alpha
Classifier: Topic :: Scientific/Engineering :: Artificial Intelligence
Classifier: License :: OSI Approved :: GNU Library or Lesser General Public License (LGPL)
Classifier: Intended Audience :: Science/Research
Classifier: Programming Language :: Python :: 3 :: Only
Classifier: Programming Language :: Python :: 3.6
Classifier: Programming Language :: Python :: 3.7
Requires-Python: >=3.6
Requires-Dist: deap
Requires-Dist: dill
Requires-Dist: numpy
Requires-Dist: pyyaml
Requires-Dist: scipy
Requires-Dist: sympy
Requires-Dist: toolz
Requires-Dist: pyzmq
Requires-Dist: matplotlib
Requires-Dist: cache.py (==0.1.3)
Requires-Dist: deprecated
Requires-Dist: stopit
Provides-Extra: gui
Requires-Dist: gooey (>=1.0.0) ; extra == 'gui'
